{
  "version": 1,
  "image": "dogs/dog_16/sprite_000.png",
  "mask": "dogs/dog_16/sprite_mask_000.png",
  "sourceVariant": "dogs/dog_16/variant_000.png",
  "sourceBox": [
    1161,
    3003,
    1425,
    3291
  ],
  "spriteBox": [
    1244,
    3063,
    1354,
    3226
  ],
  "cleanupBox": [
    1223,
    3059,
    1363,
    3230
  ],
  "width": 110,
  "height": 163,
  "anchorX": 0.4455,
  "anchorY": 0.5399,
  "technique": "model-grounded-sam2-v2",
  "quality": {
    "visibleCoverage": 0.1266,
    "strongCoverage": 0.1198,
    "bboxCoverage": 0.2079,
    "edgeTouches": 0,
    "fullCropLike": false,
    "pickupUsable": true,
    "backgroundFallback": false,
    "templateFallback": false
  }
}