{
  "id": "mexico_yucatan_cenote_ruins_dog_65e4",
  "name": "Level mexico_yucatan_cenote_ruins_dog_65e4 (clean_old_cartoon)",
  "width": 2560,
  "height": 3840,
  "bwImage": "levels/mexico_yucatan_cenote_ruins_dog_65e4/bw.png",
  "colorImage": "levels/mexico_yucatan_cenote_ruins_dog_65e4/color.png",
  "dogs": [
    {
      "id": "dog_00",
      "x": 845,
      "y": 2115,
      "r": 50,
      "sprite": {
        "image": "levels/mexico_yucatan_cenote_ruins_dog_65e4/dogs/dog_00/sprite_000.png",
        "x": 788,
        "y": 2043,
        "width": 116,
        "height": 146,
        "anchorX": 0.4914,
        "anchorY": 0.4932,
        "cleanup": {
          "x": 783,
          "y": 2038,
          "width": 126,
          "height": 156
        }
      }
    },
    {
      "id": "dog_01",
      "x": 522,
      "y": 2617,
      "r": 50,
      "sprite": {
        "image": "levels/mexico_yucatan_cenote_ruins_dog_65e4/dogs/dog_01/sprite_000.png",
        "x": 465,
        "y": 2548,
        "width": 119,
        "height": 151,
        "anchorX": 0.479,
        "anchorY": 0.457,
        "cleanup": {
          "x": 450,
          "y": 2533,
          "width": 144,
          "height": 173
        }
      }
    },
    {
      "id": "dog_02",
      "x": 1433,
      "y": 2383,
      "r": 50,
      "sprite": {
        "image": "levels/mexico_yucatan_cenote_ruins_dog_65e4/dogs/dog_02/sprite_000.png",
        "x": 1334,
        "y": 2277,
        "width": 191,
        "height": 222,
        "anchorX": 0.5183,
        "anchorY": 0.4775,
        "cleanup": {
          "x": 1317,
          "y": 2273,
          "width": 212,
          "height": 237
        }
      }
    },
    {
      "id": "dog_03",
      "x": 538,
      "y": 1667,
      "r": 50,
      "sprite": {
        "image": "levels/mexico_yucatan_cenote_ruins_dog_65e4/dogs/dog_03/sprite_000.png",
        "x": 479,
        "y": 1595,
        "width": 126,
        "height": 137,
        "anchorX": 0.4683,
        "anchorY": 0.5255,
        "cleanup": {
          "x": 475,
          "y": 1590,
          "width": 135,
          "height": 146
        }
      }
    },
    {
      "id": "dog_04",
      "x": 1820,
      "y": 1195,
      "r": 50,
      "sprite": {
        "image": "levels/mexico_yucatan_cenote_ruins_dog_65e4/dogs/dog_04/sprite_000.png",
        "x": 1765,
        "y": 1116,
        "width": 107,
        "height": 157,
        "anchorX": 0.514,
        "anchorY": 0.5032,
        "cleanup": {
          "x": 1675,
          "y": 1105,
          "width": 287,
          "height": 235
        }
      }
    },
    {
      "id": "dog_05",
      "x": 1034,
      "y": 2400,
      "r": 50,
      "sprite": {
        "image": "levels/mexico_yucatan_cenote_ruins_dog_65e4/dogs/dog_05/sprite_000.png",
        "x": 978,
        "y": 2325,
        "width": 104,
        "height": 145,
        "anchorX": 0.5385,
        "anchorY": 0.5172,
        "cleanup": {
          "x": 971,
          "y": 2321,
          "width": 127,
          "height": 154
        }
      }
    },
    {
      "id": "dog_06",
      "x": 1742,
      "y": 2334,
      "r": 50,
      "sprite": {
        "image": "levels/mexico_yucatan_cenote_ruins_dog_65e4/dogs/dog_06/sprite_000.png",
        "x": 1683,
        "y": 2243,
        "width": 135,
        "height": 174,
        "anchorX": 0.437,
        "anchorY": 0.523,
        "cleanup": {
          "x": 1669,
          "y": 2238,
          "width": 153,
          "height": 185
        }
      }
    },
    {
      "id": "dog_07",
      "x": 957,
      "y": 682,
      "r": 50,
      "sprite": {
        "image": "levels/mexico_yucatan_cenote_ruins_dog_65e4/dogs/dog_07/sprite_000.png",
        "x": 897,
        "y": 600,
        "width": 130,
        "height": 160,
        "anchorX": 0.4615,
        "anchorY": 0.5125,
        "cleanup": {
          "x": 885,
          "y": 595,
          "width": 150,
          "height": 176
        }
      }
    },
    {
      "id": "dog_08",
      "x": 816,
      "y": 1690,
      "r": 50,
      "sprite": {
        "image": "levels/mexico_yucatan_cenote_ruins_dog_65e4/dogs/dog_08/sprite_000.png",
        "x": 754,
        "y": 1616,
        "width": 118,
        "height": 132,
        "anchorX": 0.5254,
        "anchorY": 0.5606,
        "cleanup": {
          "x": 749,
          "y": 1612,
          "width": 127,
          "height": 140
        }
      }
    },
    {
      "id": "dog_09",
      "x": 1231,
      "y": 2048,
      "r": 50,
      "sprite": {
        "image": "levels/mexico_yucatan_cenote_ruins_dog_65e4/dogs/dog_09/sprite_000.png",
        "x": 1168,
        "y": 1971,
        "width": 165,
        "height": 170,
        "anchorX": 0.3818,
        "anchorY": 0.4529,
        "cleanup": {
          "x": 1122,
          "y": 1953,
          "width": 215,
          "height": 192
        }
      }
    },
    {
      "id": "dog_10",
      "x": 1760,
      "y": 2726,
      "r": 50,
      "sprite": {
        "image": "levels/mexico_yucatan_cenote_ruins_dog_65e4/dogs/dog_10/sprite_000.png",
        "x": 1710,
        "y": 2660,
        "width": 100,
        "height": 133,
        "anchorX": 0.5,
        "anchorY": 0.4962,
        "cleanup": {
          "x": 1664,
          "y": 2631,
          "width": 241,
          "height": 208
        }
      }
    },
    {
      "id": "dog_11",
      "x": 459,
      "y": 2149,
      "r": 50,
      "sprite": {
        "image": "levels/mexico_yucatan_cenote_ruins_dog_65e4/dogs/dog_11/sprite_000.png",
        "x": 392,
        "y": 2056,
        "width": 149,
        "height": 169,
        "anchorX": 0.4497,
        "anchorY": 0.5503,
        "cleanup": {
          "x": 386,
          "y": 2052,
          "width": 159,
          "height": 185
        }
      }
    },
    {
      "id": "dog_12",
      "x": 895,
      "y": 981,
      "r": 50,
      "sprite": {
        "image": "levels/mexico_yucatan_cenote_ruins_dog_65e4/dogs/dog_12/sprite_000.png",
        "x": 827,
        "y": 903,
        "width": 132,
        "height": 156,
        "anchorX": 0.5152,
        "anchorY": 0.5,
        "cleanup": {
          "x": 822,
          "y": 887,
          "width": 145,
          "height": 180
        }
      }
    },
    {
      "id": "dog_13",
      "x": 1507,
      "y": 1769,
      "r": 50,
      "sprite": {
        "image": "levels/mexico_yucatan_cenote_ruins_dog_65e4/dogs/dog_13/sprite_000.png",
        "x": 1449,
        "y": 1700,
        "width": 117,
        "height": 143,
        "anchorX": 0.4957,
        "anchorY": 0.4825,
        "cleanup": {
          "x": 1441,
          "y": 1678,
          "width": 136,
          "height": 170
        }
      }
    },
    {
      "id": "dog_14",
      "x": 626,
      "y": 1313,
      "r": 50,
      "sprite": {
        "image": "levels/mexico_yucatan_cenote_ruins_dog_65e4/dogs/dog_14/sprite_000.png",
        "x": 569,
        "y": 1235,
        "width": 114,
        "height": 152,
        "anchorX": 0.5,
        "anchorY": 0.5132,
        "cleanup": {
          "x": 553,
          "y": 1219,
          "width": 145,
          "height": 172
        }
      }
    },
    {
      "id": "dog_15",
      "x": 1207,
      "y": 1158,
      "r": 50,
      "sprite": {
        "image": "levels/mexico_yucatan_cenote_ruins_dog_65e4/dogs/dog_15/sprite_000.png",
        "x": 1141,
        "y": 1072,
        "width": 140,
        "height": 169,
        "anchorX": 0.4714,
        "anchorY": 0.5089,
        "cleanup": {
          "x": 1129,
          "y": 1028,
          "width": 223,
          "height": 227
        }
      }
    },
    {
      "id": "dog_16",
      "x": 1577,
      "y": 3167,
      "r": 50,
      "sprite": {
        "image": "levels/mexico_yucatan_cenote_ruins_dog_65e4/dogs/dog_16/sprite_000.png",
        "x": 1504,
        "y": 3080,
        "width": 157,
        "height": 182,
        "anchorX": 0.465,
        "anchorY": 0.478,
        "cleanup": {
          "x": 1500,
          "y": 3073,
          "width": 165,
          "height": 193
        }
      }
    },
    {
      "id": "dog_17",
      "x": 1167,
      "y": 1552,
      "r": 50,
      "sprite": {
        "image": "levels/mexico_yucatan_cenote_ruins_dog_65e4/dogs/dog_17/sprite_000.png",
        "x": 1105,
        "y": 1476,
        "width": 119,
        "height": 153,
        "anchorX": 0.521,
        "anchorY": 0.4967,
        "cleanup": {
          "x": 1100,
          "y": 1471,
          "width": 128,
          "height": 163
        }
      }
    },
    {
      "id": "dog_18",
      "x": 1344,
      "y": 2767,
      "r": 50,
      "sprite": {
        "image": "levels/mexico_yucatan_cenote_ruins_dog_65e4/dogs/dog_18/sprite_000.png",
        "x": 1233,
        "y": 2663,
        "width": 264,
        "height": 209,
        "anchorX": 0.4205,
        "anchorY": 0.4976,
        "cleanup": {
          "x": 1199,
          "y": 2659,
          "width": 302,
          "height": 253
        }
      }
    },
    {
      "id": "dog_19",
      "x": 1798,
      "y": 808,
      "r": 50,
      "sprite": {
        "image": "levels/mexico_yucatan_cenote_ruins_dog_65e4/dogs/dog_19/sprite_000.png",
        "x": 1661,
        "y": 715,
        "width": 274,
        "height": 195,
        "anchorX": 0.5,
        "anchorY": 0.4769,
        "cleanup": {
          "x": 1653,
          "y": 713,
          "width": 290,
          "height": 200
        }
      }
    },
    {
      "id": "dog_20",
      "x": 765,
      "y": 3360,
      "r": 50,
      "sprite": {
        "image": "levels/mexico_yucatan_cenote_ruins_dog_65e4/dogs/dog_20/sprite_000.png",
        "x": 695,
        "y": 3284,
        "width": 135,
        "height": 151,
        "anchorX": 0.5185,
        "anchorY": 0.5033,
        "cleanup": {
          "x": 690,
          "y": 3268,
          "width": 145,
          "height": 175
        }
      }
    },
    {
      "id": "dog_21",
      "x": 1274,
      "y": 3139,
      "r": 50,
      "sprite": {
        "image": "levels/mexico_yucatan_cenote_ruins_dog_65e4/dogs/dog_21/sprite_000.png",
        "x": 1215,
        "y": 3055,
        "width": 110,
        "height": 205,
        "anchorX": 0.5364,
        "anchorY": 0.4098,
        "cleanup": {
          "x": 1129,
          "y": 2994,
          "width": 290,
          "height": 288
        }
      }
    },
    {
      "id": "dog_22",
      "x": 1404,
      "y": 737,
      "r": 50,
      "sprite": {
        "image": "levels/mexico_yucatan_cenote_ruins_dog_65e4/dogs/dog_22/sprite_000.png",
        "x": 1345,
        "y": 659,
        "width": 119,
        "height": 154,
        "anchorX": 0.4958,
        "anchorY": 0.5065,
        "cleanup": {
          "x": 1259,
          "y": 653,
          "width": 290,
          "height": 224
        }
      }
    },
    {
      "id": "dog_23",
      "x": 2033,
      "y": 2429,
      "r": 50,
      "sprite": {
        "image": "levels/mexico_yucatan_cenote_ruins_dog_65e4/dogs/dog_23/sprite_000.png",
        "x": 1971,
        "y": 2343,
        "width": 123,
        "height": 167,
        "anchorX": 0.5041,
        "anchorY": 0.515,
        "cleanup": {
          "x": 1959,
          "y": 2339,
          "width": 165,
          "height": 178
        }
      }
    },
    {
      "id": "dog_24",
      "x": 763,
      "y": 2919,
      "r": 50,
      "sprite": {
        "image": "levels/mexico_yucatan_cenote_ruins_dog_65e4/dogs/dog_24/sprite_000.png",
        "x": 702,
        "y": 2839,
        "width": 130,
        "height": 162,
        "anchorX": 0.4692,
        "anchorY": 0.4938,
        "cleanup": {
          "x": 622,
          "y": 2834,
          "width": 286,
          "height": 223
        }
      }
    },
    {
      "id": "dog_25",
      "x": 1988,
      "y": 3009,
      "r": 50,
      "sprite": {
        "image": "levels/mexico_yucatan_cenote_ruins_dog_65e4/dogs/dog_25/sprite_000.png",
        "x": 1932,
        "y": 2931,
        "width": 114,
        "height": 163,
        "anchorX": 0.4912,
        "anchorY": 0.4785,
        "cleanup": {
          "x": 1845,
          "y": 2902,
          "width": 288,
          "height": 252
        }
      }
    },
    {
      "id": "dog_26",
      "x": 1892,
      "y": 1489,
      "r": 50,
      "sprite": {
        "image": "levels/mexico_yucatan_cenote_ruins_dog_65e4/dogs/dog_26/sprite_000.png",
        "x": 1827,
        "y": 1392,
        "width": 128,
        "height": 182,
        "anchorX": 0.5078,
        "anchorY": 0.533,
        "cleanup": {
          "x": 1822,
          "y": 1388,
          "width": 140,
          "height": 190
        }
      }
    },
    {
      "id": "dog_27",
      "x": 2085,
      "y": 749,
      "r": 50,
      "sprite": {
        "image": "levels/mexico_yucatan_cenote_ruins_dog_65e4/dogs/dog_27/sprite_000.png",
        "x": 2028,
        "y": 624,
        "width": 137,
        "height": 191,
        "anchorX": 0.4161,
        "anchorY": 0.6545,
        "cleanup": {
          "x": 1940,
          "y": 620,
          "width": 290,
          "height": 271
        }
      }
    },
    {
      "id": "dog_28",
      "x": 2008,
      "y": 1893,
      "r": 50,
      "sprite": {
        "image": "levels/mexico_yucatan_cenote_ruins_dog_65e4/dogs/dog_28/sprite_000.png",
        "x": 1953,
        "y": 1826,
        "width": 120,
        "height": 145,
        "anchorX": 0.4583,
        "anchorY": 0.4621,
        "cleanup": {
          "x": 1942,
          "y": 1798,
          "width": 138,
          "height": 178
        }
      }
    },
    {
      "id": "dog_29",
      "x": 484,
      "y": 3020,
      "r": 50,
      "sprite": {
        "image": "levels/mexico_yucatan_cenote_ruins_dog_65e4/dogs/dog_29/sprite_000.png",
        "x": 422,
        "y": 2931,
        "width": 126,
        "height": 159,
        "anchorX": 0.4921,
        "anchorY": 0.5597,
        "cleanup": {
          "x": 417,
          "y": 2919,
          "width": 136,
          "height": 185
        }
      }
    }
  ]
}
