{"assets":[{"bytes":1056,"description":"Green rounded rectangle surface used behind the template's primary shell action labels.","hasAlpha":true,"height":128,"id":"button-surface.primary","mimeType":"image/png","name":"Primary action surface","path":"assets/button-surface-primary.png","provenance":{"license":"CC0-1.0","sourceHash":"sha256-93318e40822c39a2ba6aec45a099d9da9bb101644198444a004cba3a354064bf","sourceId":"kenney-ui-pack-2.0","sourcePath":"PNG/Green/Double/button_rectangle_depth_gradient.png"},"sha256":"sha256-93318e40822c39a2ba6aec45a099d9da9bb101644198444a004cba3a354064bf","slotId":"button-surface","width":384},{"bytes":1080,"description":"Blue rounded rectangle surface used behind the template's secondary shell action labels.","hasAlpha":true,"height":128,"id":"button-surface.secondary","mimeType":"image/png","name":"Secondary action surface","path":"assets/button-surface-secondary.png","provenance":{"license":"CC0-1.0","sourceHash":"sha256-5cb0ab21ffb2e35c31abcaeddcabc654775d88cc1b86c950341f42d98b503e7c","sourceId":"kenney-ui-pack-2.0","sourcePath":"PNG/Blue/Double/button_rectangle_depth_gradient.png"},"sha256":"sha256-5cb0ab21ffb2e35c31abcaeddcabc654775d88cc1b86c950341f42d98b503e7c","slotId":"button-surface","width":384},{"bytes":819,"description":"Blue bordered rectangle surface used by the template's deterministic lose test action.","hasAlpha":true,"height":128,"id":"button-surface.test-lose","mimeType":"image/png","name":"Test lose action surface","path":"assets/button-surface-test-lose.png","provenance":{"license":"CC0-1.0","sourceHash":"sha256-4d141ba650e066bb7c1291a1f5924ec6334ab4f3343dc657c5c109c0bb694351","sourceId":"kenney-ui-pack-2.0","sourcePath":"PNG/Blue/Double/button_rectangle_depth_border.png"},"sha256":"sha256-4d141ba650e066bb7c1291a1f5924ec6334ab4f3343dc657c5c109c0bb694351","slotId":"button-surface","width":384},{"bytes":785,"description":"Green flat rectangle surface used by the template's deterministic win test action.","hasAlpha":true,"height":128,"id":"button-surface.test-win","mimeType":"image/png","name":"Test win action surface","path":"assets/button-surface-test-win.png","provenance":{"license":"CC0-1.0","sourceHash":"sha256-01b8240b2cbf3af3bcabb8a7daf458a111bc4f139f8d415d255a334f50754c20","sourceId":"kenney-ui-pack-2.0","sourcePath":"PNG/Green/Double/button_rectangle_depth_flat.png"},"sha256":"sha256-01b8240b2cbf3af3bcabb8a7daf458a111bc4f139f8d415d255a334f50754c20","slotId":"button-surface","width":384},{"bytes":548,"description":"White star glyph used inside the primary currency counter to identify its displayed value.","hasAlpha":true,"height":100,"id":"counter-frame.primary-currency","mimeType":"image/png","name":"Primary currency marker","path":"assets/counter-frame-primary-currency.png","provenance":{"license":"CC0-1.0","sourceHash":"sha256-cd4068a305467ff528cdc102b1ddfd8fd8c99c9f4c2e8dde403bfdda225876d7","sourceId":"kenney-game-icons-1.0","sourcePath":"PNG/White/2x/star.png"},"sha256":"sha256-cd4068a305467ff528cdc102b1ddfd8fd8c99c9f4c2e8dde403bfdda225876d7","slotId":"counter-frame","width":100},{"bytes":419,"description":"White previous-arrow glyph used inside a shell icon control that navigates backward.","hasAlpha":true,"height":100,"id":"icon-control.back","mimeType":"image/png","name":"Back icon","path":"assets/icon-control-back.png","provenance":{"license":"CC0-1.0","sourceHash":"sha256-e879a6424048aeca8e93d86074b81f2ce83267ad546ffd8f7682bf7788d76dfd","sourceId":"kenney-game-icons-1.0","sourcePath":"PNG/White/2x/previous.png"},"sha256":"sha256-e879a6424048aeca8e93d86074b81f2ce83267ad546ffd8f7682bf7788d76dfd","slotId":"icon-control","width":100},{"bytes":604,"description":"White checkmark glyph used inside a shell icon control to confirm a visible choice.","hasAlpha":true,"height":100,"id":"icon-control.confirm","mimeType":"image/png","name":"Confirm icon","path":"assets/icon-control-confirm.png","provenance":{"license":"CC0-1.0","sourceHash":"sha256-d7c1b640b57cfd8629266c010994dc58d7b64042fce50ac68959939a3dc510a4","sourceId":"kenney-game-icons-1.0","sourcePath":"PNG/White/2x/checkmark.png"},"sha256":"sha256-d7c1b640b57cfd8629266c010994dc58d7b64042fce50ac68959939a3dc510a4","slotId":"icon-control","width":100},{"bytes":337,"description":"White gamepad glyph used inside a shell icon control for the haptics preference.","hasAlpha":true,"height":100,"id":"icon-control.haptics","mimeType":"image/png","name":"Haptics icon","path":"assets/icon-control-haptics.png","provenance":{"license":"CC0-1.0","sourceHash":"sha256-a7ad442bc5afb30a65acaed7996b864cc9de30797f9426512043b4b3f4c3314b","sourceId":"kenney-game-icons-1.0","sourcePath":"PNG/White/2x/gamepad.png"},"sha256":"sha256-a7ad442bc5afb30a65acaed7996b864cc9de30797f9426512043b4b3f4c3314b","slotId":"icon-control","width":100},{"bytes":325,"description":"White house glyph used inside a shell icon control that returns to the home menu.","hasAlpha":true,"height":100,"id":"icon-control.home","mimeType":"image/png","name":"Home icon","path":"assets/icon-control-home.png","provenance":{"license":"CC0-1.0","sourceHash":"sha256-41c7b600a7a4a7dec13cb445288ebbecaa3ecdc69a86e1db794b3282c0e47721","sourceId":"kenney-game-icons-1.0","sourcePath":"PNG/White/2x/home.png"},"sha256":"sha256-41c7b600a7a4a7dec13cb445288ebbecaa3ecdc69a86e1db794b3282c0e47721","slotId":"icon-control","width":100},{"bytes":596,"description":"White muted-music glyph used inside a shell icon control for disabled music.","hasAlpha":true,"height":100,"id":"icon-control.music-off","mimeType":"image/png","name":"Music off icon","path":"assets/icon-control-music-off.png","provenance":{"license":"CC0-1.0","sourceHash":"sha256-a8503490b458cf47b712f01a5b4d25a7c0279e886237a4434d6eb22935773e98","sourceId":"kenney-game-icons-1.0","sourcePath":"PNG/White/2x/musicOff.png"},"sha256":"sha256-a8503490b458cf47b712f01a5b4d25a7c0279e886237a4434d6eb22935773e98","slotId":"icon-control","width":100},{"bytes":475,"description":"White music glyph used inside a shell icon control for enabled background music.","hasAlpha":true,"height":100,"id":"icon-control.music-on","mimeType":"image/png","name":"Music on icon","path":"assets/icon-control-music-on.png","provenance":{"license":"CC0-1.0","sourceHash":"sha256-b666a8892c785a5314b9c828affab3f5fc058e220907284f3e22a8b89088cee4","sourceId":"kenney-game-icons-1.0","sourcePath":"PNG/White/2x/musicOn.png"},"sha256":"sha256-b666a8892c785a5314b9c828affab3f5fc058e220907284f3e22a8b89088cee4","slotId":"icon-control","width":100},{"bytes":422,"description":"White forward-arrow glyph used inside a shell icon control that advances to the next step.","hasAlpha":true,"height":100,"id":"icon-control.next","mimeType":"image/png","name":"Next icon","path":"assets/icon-control-next.png","provenance":{"license":"CC0-1.0","sourceHash":"sha256-93b1852e9bbd78a97a621b074a3512104b57f09bfcdd9f61371a9a2dbbe30b56","sourceId":"kenney-game-icons-1.0","sourcePath":"PNG/White/2x/next.png"},"sha256":"sha256-93b1852e9bbd78a97a621b074a3512104b57f09bfcdd9f61371a9a2dbbe30b56","slotId":"icon-control","width":100},{"bytes":269,"description":"White pause glyph used inside the shell icon control that pauses active gameplay.","hasAlpha":true,"height":100,"id":"icon-control.pause","mimeType":"image/png","name":"Pause icon","path":"assets/icon-control-pause.png","provenance":{"license":"CC0-1.0","sourceHash":"sha256-abce8cfa932b19bfd989a8917d41e3f33c5d9622b85476a2ea1aeef5bc22ec2e","sourceId":"kenney-game-icons-1.0","sourcePath":"PNG/White/2x/pause.png"},"sha256":"sha256-abce8cfa932b19bfd989a8917d41e3f33c5d9622b85476a2ea1aeef5bc22ec2e","slotId":"icon-control","width":100},{"bytes":489,"description":"Light play-arrow glyph used inside a shell icon control that starts or resumes play.","hasAlpha":true,"height":68,"id":"icon-control.play","mimeType":"image/png","name":"Play icon","path":"assets/icon-control-play.png","provenance":{"license":"CC0-1.0","sourceHash":"sha256-60b1a1812e2263e04e590fb6f0605428930f61b905e5744c99b4bfd854ecb8f5","sourceId":"kenney-ui-pack-2.0","sourcePath":"PNG/Extra/Double/icon_play_light.png"},"sha256":"sha256-60b1a1812e2263e04e590fb6f0605428930f61b905e5744c99b4bfd854ecb8f5","slotId":"icon-control","width":60},{"bytes":539,"description":"White cross glyph used inside the shell's failure result icon control.","hasAlpha":true,"height":100,"id":"icon-control.result-fail","mimeType":"image/png","name":"Failure result icon","path":"assets/icon-control-result-fail.png","provenance":{"license":"CC0-1.0","sourceHash":"sha256-d2b55e81a6d972700e3373ed9178b935eee2e2d70b850a5a0a1905405cfdae16","sourceId":"kenney-game-icons-1.0","sourcePath":"PNG/White/2x/cross.png"},"sha256":"sha256-d2b55e81a6d972700e3373ed9178b935eee2e2d70b850a5a0a1905405cfdae16","slotId":"icon-control","width":100},{"bytes":315,"description":"White trophy glyph used inside the shell's victory result icon control.","hasAlpha":true,"height":100,"id":"icon-control.result-win","mimeType":"image/png","name":"Victory result icon","path":"assets/icon-control-result-win.png","provenance":{"license":"CC0-1.0","sourceHash":"sha256-505d5570aad9fb0478fcc1e5ec4b3bd2377f593a20013b2cff97c8e955abc515","sourceId":"kenney-game-icons-1.0","sourcePath":"PNG/White/2x/trophy.png"},"sha256":"sha256-505d5570aad9fb0478fcc1e5ec4b3bd2377f593a20013b2cff97c8e955abc515","slotId":"icon-control","width":100},{"bytes":733,"description":"Light repeat-arrow glyph used inside a shell icon control that restarts an attempt.","hasAlpha":true,"height":72,"id":"icon-control.retry","mimeType":"image/png","name":"Retry icon","path":"assets/icon-control-retry.png","provenance":{"license":"CC0-1.0","sourceHash":"sha256-be08921888d54804b6f5bbf99e8e7a230f01895c33a39956a073301cdb45fa83","sourceId":"kenney-ui-pack-2.0","sourcePath":"PNG/Extra/Double/icon_repeat_light.png"},"sha256":"sha256-be08921888d54804b6f5bbf99e8e7a230f01895c33a39956a073301cdb45fa83","slotId":"icon-control","width":82},{"bytes":629,"description":"White return-arrow glyph used inside a shell icon control that leaves the current view.","hasAlpha":true,"height":100,"id":"icon-control.return","mimeType":"image/png","name":"Return icon","path":"assets/icon-control-return.png","provenance":{"license":"CC0-1.0","sourceHash":"sha256-d0e9fbbf5e4cb6847bc5961c8809fbddb0ca98447a2b67fb2daed5e3c67a7fcd","sourceId":"kenney-game-icons-1.0","sourcePath":"PNG/White/2x/return.png"},"sha256":"sha256-d0e9fbbf5e4cb6847bc5961c8809fbddb0ca98447a2b67fb2daed5e3c67a7fcd","slotId":"icon-control","width":100},{"bytes":863,"description":"White gear glyph used inside the shell icon control that opens game settings.","hasAlpha":true,"height":100,"id":"icon-control.settings","mimeType":"image/png","name":"Settings icon","path":"assets/icon-control-settings.png","provenance":{"license":"CC0-1.0","sourceHash":"sha256-d20dd95cb1f0d527671f10ff44259c84527705fcda8ed9d74c043960fca4bb27","sourceId":"kenney-game-icons-1.0","sourcePath":"PNG/White/2x/gear.png"},"sha256":"sha256-d20dd95cb1f0d527671f10ff44259c84527705fcda8ed9d74c043960fca4bb27","slotId":"icon-control","width":100},{"bytes":529,"description":"White shopping-cart glyph used inside the shell icon control that opens the Shop page.","hasAlpha":true,"height":100,"id":"icon-control.shop","mimeType":"image/png","name":"Shop icon","path":"assets/icon-control-shop.png","provenance":{"license":"CC0-1.0","sourceHash":"sha256-919a8e826f1dd6fda88671e6d8ff52691d93ca7dfa67868ee12a67b9290cc665","sourceId":"kenney-game-icons-1.0","sourcePath":"PNG/White/2x/shoppingCart.png"},"sha256":"sha256-919a8e826f1dd6fda88671e6d8ff52691d93ca7dfa67868ee12a67b9290cc665","slotId":"icon-control","width":100},{"bytes":956,"description":"Blue square button surface used behind a standalone top-bar shell icon control.","hasAlpha":true,"height":128,"id":"icon-control.surface","mimeType":"image/png","name":"Icon control surface","path":"assets/icon-control-surface.png","provenance":{"license":"CC0-1.0","sourceHash":"sha256-cb40b01ff701c9edc6f6814bfec3a3ccb1ab443ad044613909df53e3b6fc09bc","sourceId":"kenney-ui-pack-2.0","sourcePath":"PNG/Blue/Double/button_square_depth_gradient.png"},"sha256":"sha256-cb40b01ff701c9edc6f6814bfec3a3ccb1ab443ad044613909df53e3b6fc09bc","slotId":"icon-control","width":128},{"bytes":302,"description":"White unlocked glyph used to identify a completed node in the shell's progression path.","hasAlpha":true,"height":100,"id":"progression-node.completed","mimeType":"image/png","name":"Completed progression node","path":"assets/progression-node-completed.png","provenance":{"license":"CC0-1.0","sourceHash":"sha256-28a13bb7afe7fa7fd7004bb3dcbff40c078476c21e3d76246b2ee77400cb4599","sourceId":"kenney-game-icons-1.0","sourcePath":"PNG/White/2x/unlocked.png"},"sha256":"sha256-28a13bb7afe7fa7fd7004bb3dcbff40c078476c21e3d76246b2ee77400cb4599","slotId":"progression-node","width":100},{"bytes":2661,"description":"Green round button surface used to identify the current node in the shell's progression path.","hasAlpha":true,"height":128,"id":"progression-node.current","mimeType":"image/png","name":"Current progression node","path":"assets/progression-node-current.png","provenance":{"license":"CC0-1.0","sourceHash":"sha256-cf842ce49898e2de4c10ce248341f2fef6a75b3e027218fad9112a998b3d3573","sourceId":"kenney-ui-pack-2.0","sourcePath":"PNG/Green/Double/button_round_depth_gradient.png"},"sha256":"sha256-cf842ce49898e2de4c10ce248341f2fef6a75b3e027218fad9112a998b3d3573","slotId":"progression-node","width":128},{"bytes":295,"description":"White lock glyph used to identify an unavailable node in the shell's progression path.","hasAlpha":true,"height":100,"id":"progression-node.locked","mimeType":"image/png","name":"Locked progression node","path":"assets/progression-node-locked.png","provenance":{"license":"CC0-1.0","sourceHash":"sha256-de4f91e671256321313f68727817db3d6bfd9092f627f5790ddf24cf7a0a587f","sourceId":"kenney-game-icons-1.0","sourcePath":"PNG/White/2x/locked.png"},"sha256":"sha256-de4f91e671256321313f68727817db3d6bfd9092f627f5790ddf24cf7a0a587f","slotId":"progression-node","width":100}],"contractId":"shell-presentation-v2","contractVersion":"2.0.0"}
