{
  "version": 1,
  "image": "dogs/dog_02/sprite_000.png",
  "mask": "dogs/dog_02/sprite_mask_000.png",
  "sourceVariant": "dogs/dog_02/variant_000.png",
  "sourceBox": [
    691,
    880,
    955,
    1168
  ],
  "spriteBox": [
    763,
    938,
    878,
    1070
  ],
  "cleanupBox": [
    753,
    934,
    893,
    1100
  ],
  "width": 115,
  "height": 132,
  "anchorX": 0.5217,
  "anchorY": 0.6818,
  "technique": "model-grounded-sam2-v2",
  "quality": {
    "visibleCoverage": 0.1062,
    "strongCoverage": 0.1003,
    "bboxCoverage": 0.1745,
    "edgeTouches": 0,
    "fullCropLike": false,
    "pickupUsable": true,
    "backgroundFallback": false,
    "templateFallback": false
  }
}