{
  "version": 1,
  "image": "dogs/dog_11/sprite_000.png",
  "mask": "dogs/dog_11/sprite_mask_000.png",
  "sourceVariant": "dogs/dog_11/variant_000.png",
  "sourceBox": [
    875,
    1957,
    1423,
    2505
  ],
  "spriteBox": [
    1098,
    2149,
    1208,
    2287
  ],
  "cleanupBox": [
    1004,
    2091,
    1294,
    2376
  ],
  "width": 110,
  "height": 138,
  "anchorX": 0.4636,
  "anchorY": 0.5942,
  "technique": "model-grounded-sam2-v2",
  "quality": {
    "visibleCoverage": 0.0278,
    "strongCoverage": 0.0264,
    "bboxCoverage": 0.0442,
    "edgeTouches": 0,
    "fullCropLike": false,
    "pickupUsable": true,
    "backgroundFallback": false,
    "templateFallback": false
  }
}