{
  "version": 1,
  "image": "dogs/dog_28/sprite_000.png",
  "mask": "dogs/dog_28/sprite_mask_000.png",
  "sourceVariant": "dogs/dog_28/variant_000.png",
  "sourceBox": [
    1040,
    1860,
    1296,
    2217
  ],
  "spriteBox": [
    1110,
    1954,
    1229,
    2126
  ],
  "cleanupBox": [
    1102,
    1946,
    1235,
    2131
  ],
  "width": 119,
  "height": 172,
  "anchorX": 0.5126,
  "anchorY": 0.5116,
  "technique": "model-grounded-sam2-v2",
  "quality": {
    "visibleCoverage": 0.1322,
    "strongCoverage": 0.1268,
    "bboxCoverage": 0.1992,
    "edgeTouches": 0,
    "fullCropLike": false,
    "pickupUsable": true,
    "backgroundFallback": false,
    "templateFallback": false
  }
}