{
  "version": 1,
  "image": "dogs/dog_12/sprite_000.png",
  "mask": "dogs/dog_12/sprite_mask_000.png",
  "sourceVariant": "dogs/dog_12/variant_000.png",
  "sourceBox": [
    1817,
    953,
    2365,
    1418
  ],
  "spriteBox": [
    2032,
    1081,
    2159,
    1230
  ],
  "cleanupBox": [
    1950,
    1066,
    2235,
    1305
  ],
  "width": 127,
  "height": 149,
  "anchorX": 0.4646,
  "anchorY": 0.5638,
  "technique": "model-grounded-sam2-v2",
  "quality": {
    "visibleCoverage": 0.0409,
    "strongCoverage": 0.0391,
    "bboxCoverage": 0.0658,
    "edgeTouches": 0,
    "fullCropLike": false,
    "pickupUsable": true,
    "backgroundFallback": false,
    "templateFallback": false
  }
}