{
  "menu": {
    "score": null,
    "majorConsensusCount": 0,
    "verdict": "fail"
  },
  "level": {
    "score": null,
    "majorConsensusCount": 0,
    "verdict": "fail"
  },
  "settings": {
    "score": null,
    "majorConsensusCount": 0,
    "verdict": "fail"
  },
  "pause": {
    "score": null,
    "majorConsensusCount": 0,
    "verdict": "no-reference"
  },
  "win": {
    "score": null,
    "majorConsensusCount": 0,
    "verdict": "fail"
  },
  "fail": {
    "score": null,
    "majorConsensusCount": 0,
    "verdict": "skipped"
  }
}
