{
  "version": 1,
  "image": "dogs/dog_13/sprite_000.png",
  "mask": "dogs/dog_13/sprite_mask_000.png",
  "sourceVariant": "dogs/dog_13/variant_000.png",
  "sourceBox": [
    679,
    1306,
    1227,
    1666
  ],
  "spriteBox": [
    908,
    1405,
    1025,
    1575
  ],
  "cleanupBox": [
    813,
    1394,
    1098,
    1579
  ],
  "width": 117,
  "height": 170,
  "anchorX": 0.3846,
  "anchorY": 0.4647,
  "technique": "model-grounded-sam2-v2",
  "quality": {
    "visibleCoverage": 0.0627,
    "strongCoverage": 0.0601,
    "bboxCoverage": 0.0895,
    "edgeTouches": 0,
    "fullCropLike": false,
    "pickupUsable": true,
    "backgroundFallback": false,
    "templateFallback": false
  }
}